{
  "unversionedId": "version-1.5/Compatibillity_Features/parameter_settings",
  "id": "version-1.5/Compatibillity_Features/parameter_settings",
  "title": "兼容配置参数",
  "description": "参数名称和值",
  "source": "@site/docs/version-1.5/Compatibillity_Features/1_parameter_settings.md",
  "sourceDirName": "version-1.5/Compatibillity_Features",
  "slug": "/version-1.5/Compatibillity_Features/parameter_settings",
  "permalink": "/docs/next/version-1.5/Compatibillity_Features/parameter_settings",
  "draft": false,
  "tags": [
    {
      "label": "Compatibility Parameters",
      "permalink": "/docs/next/tags/compatibility-parameters"
    }
  ],
  "version": "current",
  "sidebarPosition": 1,
  "frontMatter": {
    "sidebar_position": 1,
    "sidebar_label": "配置参数",
    "title": "兼容配置参数",
    "tags": [
      "Compatibility Parameters"
    ]
  },
  "sidebar": "tutorialSidebar",
  "previous": {
    "title": "附加和分离",
    "permalink": "/docs/next/Global Unique Index/attach_and_detach"
  },
  "next": {
    "title": "包",
    "permalink": "/docs/next/version-1.5/Compatibillity_Features/package"
  }
}