{
  "unversionedId": "Compatibillity_Features/package",
  "id": "version-1.5/Compatibillity_Features/package",
  "title": "Packages",
  "description": "Package Overview",
  "source": "@site/i18n/en/docusaurus-plugin-content-docs/version-1.5/Compatibillity_Features/package.md",
  "sourceDirName": "Compatibillity_Features",
  "slug": "/Compatibillity_Features/package",
  "permalink": "/en/docs/1.5/Compatibillity_Features/package",
  "draft": false,
  "tags": [
    {
      "label": "Oracle Style Packages",
      "permalink": "/en/docs/1.5/tags/oracle-style-packages"
    }
  ],
  "version": "1.5",
  "sidebarPosition": 2,
  "frontMatter": {
    "sidebar_position": 2,
    "sidebar_label": "Packages",
    "title": "Packages",
    "tags": [
      "Oracle Style Packages"
    ]
  },
  "sidebar": "version-1.5/tutorialSidebar",
  "previous": {
    "title": "Compatibility Parameters",
    "permalink": "/en/docs/1.5/Compatibillity_Features/parameter_settings"
  },
  "next": {
    "title": "Alter Table",
    "permalink": "/en/docs/1.5/Compatibillity_Features/alter_table"
  }
}